djgeojson/__init__.py
djgeojson/fields.py
djgeojson/http.py
djgeojson/models.py
djgeojson/nogeos.py
djgeojson/serializers.py
djgeojson/tests.py
djgeojson/views.py
djgeojson/templatetags/__init__.py
djgeojson/templatetags/geojson_tags.py
django_geojson-4.1.0.dist-info/LICENSE
django_geojson-4.1.0.dist-info/METADATA
django_geojson-4.1.0.dist-info/WHEEL
django_geojson-4.1.0.dist-info/top_level.txt
django_geojson-4.1.0.dist-info/RECORD
